doc8/__init__.py
doc8/__main__.py
doc8/_version.py
doc8/checks.py
doc8/main.py
doc8/parser.py
doc8/utils.py
doc8/version.py
doc8/tests/__init__.py
doc8/tests/test_checks.py
doc8/tests/test_main.py
doc8-2.0.0.dist-info/licenses/LICENSE
doc8-2.0.0.dist-info/METADATA
doc8-2.0.0.dist-info/WHEEL
doc8-2.0.0.dist-info/entry_points.txt
doc8-2.0.0.dist-info/top_level.txt
doc8-2.0.0.dist-info/RECORD
